pytryfi/__init__.py
pytryfi/const.py
pytryfi/exceptions.py
pytryfi/fiBase.py
pytryfi/fiDevice.py
pytryfi/fiPet.py
pytryfi/fiUser.py
pytryfi/ledColors.py
pytryfi/common/query.py
jldeenpytryfi-0.0.19.dist-info/LICENSE
jldeenpytryfi-0.0.19.dist-info/METADATA
jldeenpytryfi-0.0.19.dist-info/WHEEL
jldeenpytryfi-0.0.19.dist-info/top_level.txt
jldeenpytryfi-0.0.19.dist-info/RECORD
