Metadata-Version: 2.1
Name: jldeenpytryfi
Version: 0.0.19
Summary: Python Interface for TryFi Dog Collars
Home-page: https://github.com/sbabcock23/pytryfi
Author: Steve Babcock
Author-email: steve.w.babcock@gmail.com
Classifier: Programming Language :: Python :: 3
Classifier: License :: OSI Approved :: Apache Software License
Classifier: Operating System :: OS Independent
Requires-Python: >=3.6
License-File: LICENSE
Requires-Dist: requests
Requires-Dist: sentry-sdk
